safeserialize/__init__.py
safeserialize/constants.py
safeserialize/core.py
safeserialize/types/__init__.py
safeserialize/types/numpy.py
safeserialize/types/pandas.py
safeserialize/types/pytz.py
safeserialize/types/scipy.py
safeserialize/types/torch.py
safeserialize/types/stdlib/__init__.py
safeserialize/types/stdlib/collections.py
safeserialize/types/stdlib/datetime.py
safeserialize/types/stdlib/decimal.py
safeserialize/types/stdlib/fractions.py
safeserialize/types/stdlib/pathlib.py
safeserialize/types/stdlib/uuid.py
safeserialize-0.0.7.dist-info/licenses/LICENSE
safeserialize-0.0.7.dist-info/METADATA
safeserialize-0.0.7.dist-info/WHEEL
safeserialize-0.0.7.dist-info/top_level.txt
safeserialize-0.0.7.dist-info/RECORD
