Metadata-Version: 2.4
Name: safeserialize
Version: 0.0.7
Summary: A safe serialization library for Python
Author-email: Thomas Germer <Thomas.Germer@hhu.de>
Project-URL: Homepage, https://github.com/99991/safeserialize
Project-URL: Bug Tracker, https://github.com/99991/safeserialize/issues
Requires-Python: >=3.9
License-File: LICENSE
Provides-Extra: test
Requires-Dist: pytest; extra == "test"
Requires-Dist: numpy; extra == "test"
Requires-Dist: scipy; extra == "test"
Requires-Dist: pandas; extra == "test"
Requires-Dist: torch; extra == "test"
Dynamic: license-file
